<root>
 <level name="2_2"><end2_2 show="效忠子爵"><t0>我效忠元始子爵。
</t0><t1>:...</t1></end2_2><start2_2 show="交流方式"><s4>1</s4><s5>-1</s5><s6>1</s6><s7>-1</s7><s8>1</s8><t0>巫咸将夕降兮
</t0><t1>:圜之能周兮，夫孰异道而相安屈心而抑志兮，忍尤而攘诟(9):固乱流其鲜终兮，浞又贪夫厥家(9):怀椒糈而要之(2):后辛之菹醢兮，殷宗用而不长(9)
</t1><t2>广明元年（880年）十一月十七日，东都留守刘允章迎黄巢军入洛阳
</t2><t3>:记得当年草上飞，铁衣著尽著僧衣(4):北邙山草又青青，今日销魂事可明(4):飒飒西风满院栽，蕊寒香冷蝶难来(5):诏选将军护北戎，身骑白马臂彤弓(4)
</t3><t4>:天津桥上无人识，独倚栏干看落晖(6):柳营远识金貂贵，榆塞遥知玉帐雄(5):千度仓兮万丝箱，黄巢过后犹残半(5):愁云惨淡罩群峰，昭阳冈上，坟列千层(5)
</t4><t5>:秋槛鼓鼙惊朔雪，晓阶旗纛起边风(6):也有周秦并汉魏，齐梁晋宋唐宗，哀声歌举送英雄(6):他年我若为青帝， 报与桃花一处开(7):若教阴晴都相似，争表梁王造化工(6)
</t5><t6>:一种山前路入秦，嵩山堪爱此伤神(7):取吾首送天子，可得富贵，毋为他人利(8):蓬莱每望平安火，应奏班超定远功(7):冲天香阵透长安，满城尽带黄金甲(7)
</t6><t7>尚让厨中食木皮，黄巢机上刲人肉(9)
</t7><t8>同是乾坤事不同，雨丝飞洒日轮中(9)
</t8><t9>:...
</t9><t10>:...</t10></start2_2></level>
</root>
